dilum_sentiment_basic/__init__.py
dilum_sentiment_basic/frontend/build/index.html
dilum_sentiment_basic/frontend/build/vite.svg
dilum_sentiment_basic/frontend/build/assets/index-093b03e1.js
dilum_sentiment_basic/frontend/build/assets/index-10fc1370.css
dilum_sentiment_basic-0.0.3.dist-info/LICENSE
dilum_sentiment_basic-0.0.3.dist-info/METADATA
dilum_sentiment_basic-0.0.3.dist-info/WHEEL
dilum_sentiment_basic-0.0.3.dist-info/top_level.txt
dilum_sentiment_basic-0.0.3.dist-info/RECORD
