Metadata-Version: 2.1
Name: dilum-sentiment-basic
Version: 0.0.3
Summary: Streamlit custom component to display sentiment analysis data.
Home-page: https://dilums.com
Author: Dilum Sanjaya
Author-email: info@dilums.com
Requires-Python: >=3.7
License-File: LICENSE
Requires-Dist: streamlit >=0.63
